hass_nabucasa/__init__.py
hass_nabucasa/account_link.py
hass_nabucasa/acme.py
hass_nabucasa/auth.py
hass_nabucasa/client.py
hass_nabucasa/cloud_api.py
hass_nabucasa/cloudhooks.py
hass_nabucasa/const.py
hass_nabucasa/google_report_state.py
hass_nabucasa/ice_servers.py
hass_nabucasa/iot.py
hass_nabucasa/iot_base.py
hass_nabucasa/py.typed
hass_nabucasa/remote.py
hass_nabucasa/thingtalk.py
hass_nabucasa/utils.py
hass_nabucasa/voice.py
hass_kingsignal-0.87.0.dist-info/LICENSE
hass_kingsignal-0.87.0.dist-info/METADATA
hass_kingsignal-0.87.0.dist-info/WHEEL
hass_kingsignal-0.87.0.dist-info/top_level.txt
hass_kingsignal-0.87.0.dist-info/RECORD
